pbcpy/__init__.py
pbcpy/atom.py
pbcpy/base.py
pbcpy/constants.py
pbcpy/grid.py
pbcpy/system.py
pbcpy/formats/__init__.py
pbcpy/formats/qepp.py
pbcpy/formats/xsf.py
pbcpy-0.1.0.dist-info/DESCRIPTION.rst
pbcpy-0.1.0.dist-info/METADATA
pbcpy-0.1.0.dist-info/RECORD
pbcpy-0.1.0.dist-info/WHEEL
pbcpy-0.1.0.dist-info/metadata.json
pbcpy-0.1.0.dist-info/top_level.txt
