Metadata-Version: 2.0
Name: pbcpy
Version: 0.1.0
Summary: A toolbox to make it easier to deal with materials under
Home-page: https://gitlab.com/ales.genova/pbcpy/
Author: A. Genova
Author-email: ales.genova@gmail.com
License: MIT
Platform: UNKNOWN
Classifier: Development Status :: 4 - Beta
Classifier: Intended Audience :: Science/Research
Classifier: License :: OSI Approved :: MIT License
Classifier: Programming Language :: Python :: 3
Classifier: Topic :: Scientific/Engineering :: Chemistry
Classifier: Topic :: Scientific/Engineering :: Physics
Requires-Dist: numpy (>=1.6.0)
Requires-Dist: scipy (>=0.10.0)
